intel_extension_for_deepspeed/__init__.py
intel_extension_for_deepspeed/xpu_accelerator.py
intel_extension_for_deepspeed/op_builder/__init__.py
intel_extension_for_deepspeed/op_builder/builder.py
intel_extension_for_deepspeed/op_builder/cpu_adagrad.py
intel_extension_for_deepspeed/op_builder/cpu_adam.py
intel_extension_for_deepspeed/op_builder/fused_adam.py
intel_extension_for_deepspeed/op_builder/quantizer.py
intel_extension_for_deepspeed/op_builder/transformer.py
intel_extension_for_deepspeed/op_builder/transformer_inference.py
intel_extension_for_deepspeed/op_builder/utils.py
intel_extension_for_deepspeed/op_builder/csrc/adagrad/cpu_adagrad.dp.cpp
intel_extension_for_deepspeed/op_builder/csrc/adam/cpu_adam.dp.cpp
intel_extension_for_deepspeed/op_builder/csrc/adam/custom_sycl_kernel.dp.cpp
intel_extension_for_deepspeed/op_builder/csrc/adam/fused_adam_frontend.cpp
intel_extension_for_deepspeed/op_builder/csrc/adam/multi_tensor_adam.dp.cpp
intel_extension_for_deepspeed/op_builder/csrc/includes/Timer.hpp
intel_extension_for_deepspeed/op_builder/csrc/includes/common.hpp
intel_extension_for_deepspeed/op_builder/csrc/includes/context.hpp
intel_extension_for_deepspeed/op_builder/csrc/includes/cpu_adagrad.hpp
intel_extension_for_deepspeed/op_builder/csrc/includes/cpu_adam.hpp
intel_extension_for_deepspeed/op_builder/csrc/includes/custom_sycl_layers.hpp
intel_extension_for_deepspeed/op_builder/csrc/includes/dropout.hpp
intel_extension_for_deepspeed/op_builder/csrc/includes/ds_transformer_sycl.hpp
intel_extension_for_deepspeed/op_builder/csrc/includes/feed_forward.hpp
intel_extension_for_deepspeed/op_builder/csrc/includes/gelu.hpp
intel_extension_for_deepspeed/op_builder/csrc/includes/gemm_test.hpp
intel_extension_for_deepspeed/op_builder/csrc/includes/general_kernels.hpp
intel_extension_for_deepspeed/op_builder/csrc/includes/multi_tensor_apply.dp.hpp
intel_extension_for_deepspeed/op_builder/csrc/includes/normalize_layer.hpp
intel_extension_for_deepspeed-0.9.4.dist-info/LICENSE
intel_extension_for_deepspeed-0.9.4.dist-info/METADATA
intel_extension_for_deepspeed-0.9.4.dist-info/WHEEL
intel_extension_for_deepspeed-0.9.4.dist-info/top_level.txt
intel_extension_for_deepspeed-0.9.4.dist-info/RECORD
