Metadata-Version: 2.1
Name: intel-extension-for-deepspeed
Version: 0.9.4
Summary: Intel® Extension for DeepSpeed*
Home-page: https://github.com/intel/intel-extension-for-deepspeed
Author: Intel Corporation
License: https://opensource.org/license/mit
Platform: UNKNOWN
License-File: LICENSE
Requires-Dist: setuptools
